src/__init__.py
src/main.py
tests/__init__.py
tests/test_add.py
lucas_pypicd-1.0.3.dist-info/METADATA
lucas_pypicd-1.0.3.dist-info/WHEEL
lucas_pypicd-1.0.3.dist-info/top_level.txt
lucas_pypicd-1.0.3.dist-info/RECORD
