Metadata-Version: 2.4
Name: Lucas_pypicd
Version: 1.0.3
Summary: GitHub_Actions with Roman
Author: Kluklas
Author-email: kluklassmr@gmail.com
Requires-Dist: pytest
Requires-Dist: flake8
Dynamic: author
Dynamic: author-email
Dynamic: requires-dist
Dynamic: summary
